plone.stringinterp-2.0.3-py3.13-nspkg.pth
plone/stringinterp/__init__.py
plone/stringinterp/adapters.py
plone/stringinterp/browser.py
plone/stringinterp/configure.zcml
plone/stringinterp/dollarReplace.py
plone/stringinterp/interfaces.py
plone/stringinterp/tests/__init__.py
plone/stringinterp/tests/interpolationTests.txt
plone/stringinterp/tests/moreSubstitutionTests.txt
plone/stringinterp/tests/substitutionTests.txt
plone/stringinterp/tests/testDocTests.py
plone/stringinterp/tests/wrapperTests.txt
plone_stringinterp-2.0.3.dist-info/METADATA
plone_stringinterp-2.0.3.dist-info/WHEEL
plone_stringinterp-2.0.3.dist-info/entry_points.txt
plone_stringinterp-2.0.3.dist-info/namespace_packages.txt
plone_stringinterp-2.0.3.dist-info/top_level.txt
plone_stringinterp-2.0.3.dist-info/RECORD
